SimpleDL/__init__.py
SimpleDL/setup.py
SimpleDL/train.py
SimpleDL/dataset/__init__.py
SimpleDL/dataset/basic_dataset.py
SimpleDL/dataset/basic_transform.py
SimpleDL/dataset/dataset_behavior.py
SimpleDL/model/__init__.py
SimpleDL/model/losses.py
SimpleDL/option/__init__.py
SimpleDL/option/load_options.py
SimpleDL/trainer/__init__.py
SimpleDL/trainer/basic_trainer.py
SimpleDL/utils/__init__.py
SimpleDL/utils/logger.py
SimpleDL/utils/meter.py
SimpleDLCV-0.0.6.dist-info/METADATA
SimpleDLCV-0.0.6.dist-info/WHEEL
SimpleDLCV-0.0.6.dist-info/top_level.txt
SimpleDLCV-0.0.6.dist-info/RECORD
