Metadata-Version: 2.1
Name: SimpleDLCV
Version: 0.0.6
Summary: UNKNOWN
Home-page: https://gitee.com/small_eyes_zdh/SimpleDL
Author: zdh
Author-email: zhoudonghui0124@163.com
License: UNKNOWN
Keywords: pytorch dl cv
Platform: UNKNOWN
Classifier: Operating System :: OS Independent
Classifier: Intended Audience :: Developers
Classifier: License :: OSI Approved :: MIT License
Classifier: Programming Language :: Python :: 3.8
Requires-Python: >=3.8
Requires-Dist: tqdm (>=4.64.1)
Requires-Dist: pyyaml (==6.0)
